iabs2rel/__init__.py
iabs2rel/aliases.py
iabs2rel/main.py
iabs2rel/utils.py
iabs2rel/cli/__init__.py
iabs2rel/cli/dir.py
iabs2rel/cli/file.py
iabs2rel/cli/utils.py
tests/__init__.py
tests/config.py
tests/main.py
tests/test_dir_imports.py
tests/test_file_imports.py
tests/utils.py
tests/data/__init__.py
tests/data/input/__init__.py
tests/data/input/simple.py
tests/data/input/p/__init__.py
tests/data/input/p/file.py
tests/data/input/p/simple2.py
tests/data/input/p2/__init__.py
tests/data/input/p2/file.py
tests/data/input/p2/p3/__init__.py
tests/data/input/p2/p3/file4.py
tests/data/input/p2/p3/simple3.py
tests/data/input/package/__init__.py
tests/data/input/package/file1.py
tests/data/input/package/file2.py
iabs2rel-0.1.0.dist-info/LICENSE
iabs2rel-0.1.0.dist-info/METADATA
iabs2rel-0.1.0.dist-info/WHEEL
iabs2rel-0.1.0.dist-info/entry_points.txt
iabs2rel-0.1.0.dist-info/top_level.txt
iabs2rel-0.1.0.dist-info/RECORD
