Metadata-Version: 2.1
Name: iabs2rel
Version: 0.1.0
Summary: A Python utility / library to convert absolute Python imports to relative
Home-page: https://github.com/PasaOpasen/iabs2rel
Author: Demetry Pascal
Author-email: qtckpuhdsa@gmail.com
Maintainer: Demetry Pascal
License: MIT
Keywords: import,absolute,relative,cli
Platform: UNKNOWN
Classifier: Programming Language :: Python :: 3.8
Classifier: License :: OSI Approved :: MIT License
Classifier: Operating System :: OS Independent
Classifier: Topic :: Software Development :: Libraries :: Python Modules
Requires-Dist: typing-extensions
